sam_tags/__init__.py
sam_tags/community/__init__.py
sam_tags/community/bwa_tag.py
sam_tags/community/cellranger_tag.py
sam_tags/sam_tag.py
sam_tags/standard_tag.py
sam_tags-0.1.0.dist-info/LICENSE
sam_tags-0.1.0.dist-info/METADATA
sam_tags-0.1.0.dist-info/WHEEL
sam_tags-0.1.0.dist-info/RECORD
