Metadata-Version: 2.1
Name: sam_tags
Version: 0.1.0
Summary: SAM tags
Home-page: https://github.com/msto/sam_tags
Author: Matt Stone
Author-email: matt@fulcrumgenomics.com
Requires-Python: >=3.11,<4.0
Classifier: Development Status :: 3 - Alpha
Classifier: Programming Language :: Python :: 3
Classifier: Programming Language :: Python :: 3.11
Classifier: Programming Language :: Python :: 3.12
Project-URL: Bug Tracker, https://github.com/msto/sam_tags/issues
Project-URL: Documentation, https://github.com/msto/sam_tags
Project-URL: Repository, https://github.com/msto/sam_tags
